{
  "unversionedId": "FAQ",
  "id": "FAQ",
  "title": "Ugh! Why is it doing that thing",
  "description": "Common Error Messages and What to Do",
  "source": "@site/docs/FAQ.md",
  "sourceDirName": ".",
  "slug": "/FAQ",
  "permalink": "/docs/FAQ",
  "draft": false,
  "editUrl": "https://github.com/TrunkRecorder/trunkrecorder.github.io/tree/main/docs/FAQ.md",
  "tags": [],
  "version": "current",
  "sidebarPosition": 6,
  "frontMatter": {
    "sidebar_label": "FAQ",
    "sidebar_position": 6
  },
  "sidebar": "tutorialSidebar",
  "previous": {
    "title": "Debugging",
    "permalink": "/docs/DEBUG"
  },
  "next": {
    "title": "Linux Install",
    "permalink": "/docs/Install/INSTALL-LINUX"
  }
}